[
  {
    "title": "New Paper by CDDS@UIUC!",
    "description": "Cristi has a new paper on paleoclimate in PNAS.",
    "image": {
      "url": "images/features/noun_branding_1885335.svg",
      "width": 80,
      "height": 80
    }
  },
  {
    "title": "New members joining CDDS@UIUC!",
    "description": "Maile and Pappu joined in Fall 2022 as Ph.D. students.",
    "image": {
      "url": "images/features/noun_The Process_1885341.svg",
      "width": 80,
      "height": 80
    }
  },
  {
    "title": "CDDS members talking at AGU 2022!",
    "description": "Adam and Rachel will be giving talks at AGU's fall meeting in Chicago this year.",
    "image": {
      "url": "images/features/noun_3d modeling_1885342.svg",
      "width": 80,
      "height": 80
    }
  }
]
